odoo/addons/project_task_stock_product_set/README.rst
odoo/addons/project_task_stock_product_set/__init__.py
odoo/addons/project_task_stock_product_set/__manifest__.py
odoo/addons/project_task_stock_product_set/i18n/es.po
odoo/addons/project_task_stock_product_set/i18n/it.po
odoo/addons/project_task_stock_product_set/i18n/project_task_stock_product_set.pot
odoo/addons/project_task_stock_product_set/i18n/pt_BR.po
odoo/addons/project_task_stock_product_set/models/__init__.py
odoo/addons/project_task_stock_product_set/models/product_set_line.py
odoo/addons/project_task_stock_product_set/readme/CONFIGURE.md
odoo/addons/project_task_stock_product_set/readme/CONTRIBUTORS.md
odoo/addons/project_task_stock_product_set/readme/DESCRIPTION.md
odoo/addons/project_task_stock_product_set/readme/USAGE.md
odoo/addons/project_task_stock_product_set/security/ir.model.access.csv
odoo/addons/project_task_stock_product_set/static/description/icon.png
odoo/addons/project_task_stock_product_set/static/description/index.html
odoo/addons/project_task_stock_product_set/tests/__init__.py
odoo/addons/project_task_stock_product_set/tests/test_project_task_stock_product_set.py
odoo/addons/project_task_stock_product_set/views/project_task_view.xml
odoo/addons/project_task_stock_product_set/wizard/__init__.py
odoo/addons/project_task_stock_product_set/wizard/project_task_stock_product_set_wizard.py
odoo/addons/project_task_stock_product_set/wizard/project_task_stock_product_set_wizard_view.xml
odoo_addon_project_task_stock_product_set-18.0.1.0.0.3.dist-info/METADATA
odoo_addon_project_task_stock_product_set-18.0.1.0.0.3.dist-info/WHEEL
odoo_addon_project_task_stock_product_set-18.0.1.0.0.3.dist-info/top_level.txt
odoo_addon_project_task_stock_product_set-18.0.1.0.0.3.dist-info/RECORD
