Metadata-Version: 2.1
Name: odoo-addon-project_task_stock_product_set
Version: 18.0.1.0.0.3
Requires-Python: >=3.10
Requires-Dist: odoo-addon-product_set==18.0.*
Requires-Dist: odoo-addon-project_task_stock==18.0.*
Requires-Dist: odoo==18.0.*
Summary: Project Task Stock Product Set
Home-page: https://github.com/OCA/project
License: AGPL-3
Author: Tecnativa, Odoo Community Association (OCA)
Author-email: support@odoo-community.org
Classifier: Programming Language :: Python
Classifier: Framework :: Odoo
Classifier: Framework :: Odoo :: 18.0
Classifier: License :: OSI Approved :: GNU Affero General Public License v3
